TinyAutoML/Estimator.py
TinyAutoML/EstimatorCV.py
TinyAutoML/MetaPipeline.py
TinyAutoML/MetaPipelineCV.py
TinyAutoML/__init__.py
TinyAutoML/builders.py
TinyAutoML/Models/BestModel.py
TinyAutoML/Models/BestModelCV.py
TinyAutoML/Models/DemocraticModel.py
TinyAutoML/Models/DemocraticModelCV.py
TinyAutoML/Models/EstimatorsPool.py
TinyAutoML/Models/EstimatorsPoolCV.py
TinyAutoML/Models/MetaModel.py
TinyAutoML/Models/OneRulerForAll.py
TinyAutoML/Models/OneRulerForAllCV.py
TinyAutoML/Models/__init__.py
TinyAutoML/Models/EstimatorPools/EstimatorPool.py
TinyAutoML/Models/EstimatorPools/EstimatorPoolCV.py
TinyAutoML/Models/EstimatorPools/__init__.py
TinyAutoML/Models/MetaModels/BestModel.py
TinyAutoML/Models/MetaModels/DemocraticModel.py
TinyAutoML/Models/MetaModels/OneRulerForAll.py
TinyAutoML/Models/MetaModels/__init__.py
TinyAutoML/Preprocessing/LassoFeatureSelection.py
TinyAutoML/Preprocessing/LassoFeatureSelectionConcurrence.py
TinyAutoML/Preprocessing/LassoFeatureSelectionParallel.py
TinyAutoML/Preprocessing/LassoSelectorTransformer.py
TinyAutoML/Preprocessing/NonStationarityCorrector.py
TinyAutoML/Preprocessing/PenalizationGrid.py
TinyAutoML/Preprocessing/__init__.py
TinyAutoML/constants/GLOBAL_PARAMS.py
TinyAutoML/constants/__init__.py
TinyAutoML/constants/gsp.py
TinyAutoML/support/MyTools.py
TinyAutoML/support/__init__.py
examples/__init__.py
examples/example.py
examples/example_utils.py
support/MyTools.py
support/__init__.py
support/SupportClasses/DemocraticModel.py
support/SupportClasses/EstimatorsPool.py
support/SupportClasses/FeatureSelection.py
support/SupportClasses/LassoSelector.py
support/SupportClasses/LassoSelectorTransformer.py
support/SupportClasses/MetaModel.py
support/SupportClasses/NonStationarityCorrector.py
support/SupportClasses/OneRulerForAll.py
support/SupportClasses/PenalizationGrid.py
support/SupportClasses/__init__.py
support/constants/GLOBAL_PARAMS.py
support/constants/__init__.py
support/constants/gsp.py
test_/test_MyTools.py
TinyAutoML-0.2.4.1.dist-info/LICENSE.txt
TinyAutoML-0.2.4.1.dist-info/METADATA
TinyAutoML-0.2.4.1.dist-info/WHEEL
TinyAutoML-0.2.4.1.dist-info/top_level.txt
TinyAutoML-0.2.4.1.dist-info/RECORD
